{
  "display": {
    "icon": {
      "item": "immersiveintelligence:machinegun"
    },
    "title": {
      "translate": "advancement.immersiveintelligence.craft_mg"
    },
    "description": {
      "translate": "advancement.immersiveintelligence.craft_mg.desc"
    }
  },
  "parent": "immersiveintelligence:main/root",
  "criteria": {
    "craft_hammer": {
      "trigger": "minecraft:inventory_changed",
      "conditions": {
        "items": [
          {
            "item": "immersiveintelligence:machinegun"
          }
        ]
      }
    }
  }
}